AUTHORS.rst
CONTRIBUTING.rst
HISTORY.rst
LICENSE
MANIFEST.in
README.rst
setup.py
pyadbc/__init__.py
pyadbc/pyadbc.py
pyadbc.egg-info/PKG-INFO
pyadbc.egg-info/SOURCES.txt
pyadbc.egg-info/dependency_links.txt
pyadbc.egg-info/not-zip-safe
pyadbc.egg-info/top_level.txt