Metadata-Version: 1.1
Name: pyadbc
Version: 0.1.0
Summary: PyADBC: Design by Contract in Python
Home-page: https://github.com/tarmstrong/pyadbc
Author: Tavish Armstrong
Author-email: tavisharmstrong@gmail.com
License: BSD
Keywords: pyadbc
Platform: UNKNOWN
Classifier: Development Status :: 2 - Pre-Alpha
Classifier: Intended Audience :: Developers
Classifier: License :: OSI Approved :: BSD License
Classifier: Natural Language :: English
Classifier: Programming Language :: Python :: 2
Classifier: Programming Language :: Python :: 2.6
Classifier: Programming Language :: Python :: 2.7
